README.md
setup.py
wpool.py
wpool.egg-info/PKG-INFO
wpool.egg-info/SOURCES.txt
wpool.egg-info/dependency_links.txt
wpool.egg-info/top_level.txt