Metadata-Version: 1.0
Name: wpool
Version: 0.1.0
Summary: Pub/sub worker pool
Home-page: https://github.com/ewilazarus/wpool
Author: Gabriel Lima
Author-email: gvclima@gmail.com
License: MIT
Keywords: pub/sub
Platform: UNKNOWN
